remotebmi/__init__.py
remotebmi/py.typed
remotebmi/reserve.py
remotebmi/client/__init__.py
remotebmi/client/apptainer.py
remotebmi/client/client.py
remotebmi/client/docker.py
remotebmi/client/utils.py
remotebmi/server/__init__.py
remotebmi/server/api.py
remotebmi/server/build.py
remotebmi/server/openapi.yaml
remotebmi-0.1.0.dist-info/METADATA
remotebmi-0.1.0.dist-info/WHEEL
remotebmi-0.1.0.dist-info/entry_points.txt
remotebmi-0.1.0.dist-info/RECORD
