Metadata-Version: 2.3
Name: remotebmi
Version: 0.1.0
Summary: Basic Model Interface over openapi specification
Project-URL: Homepage, https://github.com/eWaterCycle/remotebmi
Project-URL: Issues, https://github.com/eWaterCycle/remotebmi/issues
Project-URL: Documentation, https://github.com/eWaterCycle/remotebmi#readme
Project-URL: Source, https://github.com/eWaterCycle/remotebmi
License: Apache-2.0
Keywords: BMI,Basic Model Interface,ewatercycle
Classifier: Development Status :: 3 - Alpha
Classifier: Intended Audience :: Science/Research
Classifier: License :: OSI Approved :: Apache Software License
Classifier: Operating System :: OS Independent
Classifier: Programming Language :: Python
Classifier: Programming Language :: Python :: 3.10
Classifier: Programming Language :: Python :: 3.11
Classifier: Programming Language :: Python :: 3.12
Classifier: Programming Language :: Python :: 3.13
Classifier: Topic :: Scientific/Engineering
Classifier: Topic :: Utilities
Requires-Python: >=3.10
Requires-Dist: bmipy
Requires-Dist: connexion
Requires-Dist: docker
Requires-Dist: httpx>=0.27.2
Requires-Dist: numpy
Requires-Dist: uvicorn
Provides-Extra: dev
Requires-Dist: mypy; extra == 'dev'
Requires-Dist: pytest; extra == 'dev'
Requires-Dist: pytest-cov; extra == 'dev'
Requires-Dist: ruff; extra == 'dev'
Requires-Dist: types-docker; extra == 'dev'
